{
  "CodeName": "verticalbanner",
  "Name": "Vertical Image Banner",
  "Type": "live,available",
  "State": "enabled",
  "IsCollection": 0,
  "NameEN": "Vertical Banner",
  "DescEN": "",
  "ImageEN": "N/A",
  "ThumbnailEN": "N/A",
  "NameAR": "صور دعائية عمودية",
  "DescAR": "",
  "ImageAR": "N/A",
  "ThumbnailAR": "N/A",
  "Fields": [
    {
      "CodeName": "title",
      "Type": "text",
      "LookUpKey": "",
      "IsMultiLang": "1",
      "NameEN": "Section Title",
      "DescEN": "",
      "NameAR": "عنوان القسم",
      "DescAR": "",
      "ValueEN": "Offers",
      "ValueAR": "العروض"
    },
    {
      "CodeName": "bannerimage",
      "Type": "image",
      "LookUpKey": "",
      "IsMultiLang": "1",
      "NameEN": "Banner Image",
      "DescEN": "",
      "NameAR": "الصوره الدعائية",
      "DescAR": "",
      "ValueEN": "data/clearion/slide1.jpg",
      "ValueAR": "data/clearion/slide1.jpg"
    },
    {
      "CodeName": "imagelink",
      "Type": "product-or-category",
      "LookUpKey": "",
      "IsMultiLang": "0",
      "NameEN": "Image Link",
      "DescEN": "",
      "NameAR": "وصلة الصورة",
      "DescAR": "",
      "ValueEN": "",
      "ValueAR": ""
    }
  ]
}