{
    "CodeName": "05.FeaturedProductsPlus",
    "Name": "Featured Products Plus",
    "Type": "available",
    "State": "enabled",
    "IsCollection": 1,
    "CollectionNameEN": "Banners",
    "CollectionNameAR": "البنرات",
    "CollectionItemNameEN": "Banner",
    "CollectionItemNameAR": "بنر",
    "CollectionButtonNameEN": "Add New Banner",
    "CollectionButtonNameAR": "اضافة بنر جديد",
    "NameEN": "Featured Products Plus",
    "DescEN": "",
    "ImageEN": "N/A",
    "ThumbnailEN": "N/A",
    "NameAR": "المنتجات المميزة المتطورة",
    "DescAR": "",
    "ImageAR": "N/A",
    "ThumbnailAR": "N/A",
    "Fields": [
        {
            "CodeName": "FeaturedProductsPlus_SMTitle",
            "Type": "text",
            "LookUpKey": "",
            "IsMultiLang": "1",
            "NameEN": "Small Title",
            "DescEN": "",
            "NameAR": "العنوان الصغير",
            "DescAR": "",
            "ValueEN": "Featured",
            "ValueAR": "المنتجات"
        },
        {
            "CodeName": "FeaturedProductsPlus_LGTitle",
            "Type": "text",
            "LookUpKey": "",
            "IsMultiLang": "1",
            "NameEN": "Big Title",
            "DescEN": "",
            "NameAR": "العنوان الكبير",
            "DescAR": "",
            "ValueEN": "Plus",
            "ValueAR": "المميزة"
        },
        {
            "CodeName": "FPGroup1_Title",
            "Type": "text",
            "LookUpKey": "",
            "IsMultiLang": "1",
            "NameEN": "Group 1 - Title",
            "DescEN": "",
            "NameAR": "مجموعة ١ - العنوان",
            "DescAR": "",
            "ValueEN": "Latest Products",
            "ValueAR": "احدث المنتجات"
        },
        {
            "CodeName": "FPGroup1_Select",
            "Type": "tags-product",
            "LookUpKey": "",
            "IsMultiLang": "0",
            "NameEN": "Group 1 - Products",
            "DescEN": "",
            "NameAR": "مجموعة ١ - المنتجات",
            "DescAR": "",
            "ValueEN": "0,0,0,0,0,0,0,0",
            "ValueAR": "0,0,0,0,0,0,0,0"
        },
        {
            "CodeName": "FPGroup2_Title",
            "Type": "text",
            "LookUpKey": "",
            "IsMultiLang": "1",
            "NameEN": "Group 2 - Title",
            "DescEN": "",
            "NameAR": "مجموعة ٢ - العنوان",
            "DescAR": "",
            "ValueEN": "Best Seller",
            "ValueAR": "الاكثر طلباً"
        },
        {
            "CodeName": "FPGroup2_Select",
            "Type": "tags-product",
            "LookUpKey": "",
            "IsMultiLang": "0",
            "NameEN": "Group 2 - Products",
            "DescEN": "",
            "NameAR": "مجموعة ٢ - المنتجات",
            "DescAR": "",
            "ValueEN": "0,0,0,0,0,0,0,0",
            "ValueAR": "0,0,0,0,0,0,0,0"
        },
        {
            "CodeName": "FPGroup3_Title",
            "Type": "text",
            "LookUpKey": "",
            "IsMultiLang": "1",
            "NameEN": "Group 3 - Title",
            "DescEN": "",
            "NameAR": "مجموعة ٣ - العنوان",
            "DescAR": "",
            "ValueEN": "Special Products",
            "ValueAR": "المنتجات المميزة"
        },
        {
            "CodeName": "FPGroup3_Select",
            "Type": "tags-product",
            "LookUpKey": "",
            "IsMultiLang": "0",
            "NameEN": "Group 3 - Products",
            "DescEN": "",
            "NameAR": "مجموعة ٣ - المنتجات",
            "DescAR": "",
            "ValueEN": "0,0,0,0,0,0,0,0",
            "ValueAR": "0,0,0,0,0,0,0,0"
        },
        {
            "CodeName": "Banner_Check",
            "Type": "checkbox",
            "LookUpKey": "",
            "IsMultiLang": "1",
            "NameEN": "Display Banner",
            "DescEN": "",
            "NameAR": "عرض الاعلان",
            "DescAR": "",
            "ValueEN": "1",
            "ValueAR": "1"
        }
    ],
    "Collections": [
        {
            "Name": "",
            "Thumbnail": "N/A",
            "IsDefault": "1",
            "Fields": [
                {
                    "CodeName": "Banner_Image",
                    "Type": "image",
                    "LookUpKey": "",
                    "IsMultiLang": "1",
                    "NameEN": "Banner Image",
                    "DescEN": "",
                    "NameAR": "صورة البنر",
                    "DescAR": "",
                    "ValueEN": "data/elite/ad7.jpg",
                    "ValueAR": "data/elite/ad7.jpg"
                },
                {
                    "CodeName": "Banner_Link",
                    "Type": "link",
                    "LookUpKey": "",
                    "IsMultiLang": "0",
                    "NameEN": "Banner Link",
                    "DescEN": "",
                    "NameAR": "رابط البنر",
                    "DescAR": "",
                    "ValueEN": "",
                    "ValueAR": ""
                },
                {
                    "CodeName": "Banner_Width",
                    "Type": "sselect-lookup",
                    "LookUpKey": "Object_Width",
                    "IsMultiLang": "0",
                    "NameEN": "Banner Width",
                    "DescEN": "",
                    "NameAR": "عرض الاعلان",
                    "DescAR": "",
                    "ValueEN": "col-sm-6",
                    "ValueAR": "col-sm-6"
                }
            ]
        },
        {
            "Name": "",
            "Thumbnail": "N/A",
            "IsDefault": "0",
            "Fields": [
                {
                    "CodeName": "Banner_Image",
                    "Type": "image",
                    "LookUpKey": "",
                    "IsMultiLang": "1",
                    "NameEN": "Banner Image",
                    "DescEN": "",
                    "NameAR": "صورة البنر",
                    "DescAR": "",
                    "ValueEN": "data/elite/ad7.jpg",
                    "ValueAR": "data/elite/ad7.jpg"
                },
                {
                    "CodeName": "Banner_Link",
                    "Type": "link",
                    "LookUpKey": "",
                    "IsMultiLang": "0",
                    "NameEN": "Banner Link",
                    "DescEN": "",
                    "NameAR": "رابط البنر",
                    "DescAR": "",
                    "ValueEN": "",
                    "ValueAR": ""
                },
                {
                    "CodeName": "Banner_Width",
                    "Type": "sselect-lookup",
                    "LookUpKey": "Object_Width",
                    "IsMultiLang": "0",
                    "NameEN": "Banner Width",
                    "DescEN": "",
                    "NameAR": "عرض الاعلان",
                    "DescAR": "",
                    "ValueEN": "col-sm-6",
                    "ValueAR": "col-sm-6"
                }
            ]
        },
        {
            "Name": "",
            "Thumbnail": "N/A",
            "IsDefault": "0",
            "Fields": [
                {
                    "CodeName": "Banner_Image",
                    "Type": "image",
                    "LookUpKey": "",
                    "IsMultiLang": "1",
                    "NameEN": "Banner Image",
                    "DescEN": "",
                    "NameAR": "صورة البنر",
                    "DescAR": "",
                    "ValueEN": "data/elite/ad8.jpg",
                    "ValueAR": "data/elite/ad8.jpg"
                },
                {
                    "CodeName": "Banner_Link",
                    "Type": "link",
                    "LookUpKey": "",
                    "IsMultiLang": "0",
                    "NameEN": "Banner Link",
                    "DescEN": "",
                    "NameAR": "رابط البنر",
                    "DescAR": "",
                    "ValueEN": "",
                    "ValueAR": ""
                },
                {
                    "CodeName": "Banner_Width",
                    "Type": "sselect-lookup",
                    "LookUpKey": "Object_Width",
                    "IsMultiLang": "0",
                    "NameEN": "Banner Width",
                    "DescEN": "",
                    "NameAR": "عرض الاعلان",
                    "DescAR": "",
                    "ValueEN": "col-sm-6",
                    "ValueAR": "col-sm-6"
                }
            ]
        }
    ]
}